<?xml version="1.0" encoding="utf-8" ?>
<words>
  <word>
    <key>total_stars</key>
    <represent>Total</represent>
  </word>
  <word>
    <key>pack</key>
    <represent>Pack</represent>
  </word>
  <word>
    <key>company_name</key>
    <represent>White Room Games</represent>
  </word>
  <word>
    <key>kirill</key>
    <represent>Kirill Nekrasov</represent>
  </word>
  <word>
    <key>evgen</key>
    <represent>Evgeniy Khvan</represent>
  </word>
  <word>
    <key>yurii</key>
    <represent>Yurii Trofimov</represent>
  </word>
  <word>
    <key>twin_sevens</key>
    <represent>Twin Sevens</represent>
  </word>
  <word>
    <key>like_music</key>
    <represent>Do you like the music?</represent>
  </word>
  <word>
    <key>follow</key>
    <represent>Follow us</represent>
  </word>
  <word>
    <key>design</key>
    <represent>Design</represent>
  </word>
  <word>
    <key>art</key>
    <represent>Art</represent>
  </word>
  <word>
    <key>music_sounds</key>
    <represent>Music and sounds</represent>
  </word>
  <word>
    <key>code</key>
    <represent>Programming</represent>
  </word>
</words>